akmam_django_app_creator-0.1.0.dist-info/licenses/LICENSE
app_creator/__init__.py
app_creator/__main__.py
app_creator/core.py
myapp/__init__.py
myapp/admin.py
myapp/apps.py
myapp/models.py
myapp/urls.py
myapp/views.py
akmam_django_app_creator-0.1.0.dist-info/METADATA
akmam_django_app_creator-0.1.0.dist-info/WHEEL
akmam_django_app_creator-0.1.0.dist-info/entry_points.txt
akmam_django_app_creator-0.1.0.dist-info/top_level.txt
akmam_django_app_creator-0.1.0.dist-info/RECORD
